ShallowDreamTools/Functions.py
ShallowDreamTools/Lambdas.py
ShallowDreamTools/Pwn.py
ShallowDreamTools/__init__.py
ShallowDreamTools/my_function.py
ShallowDreamTools/my_head.py
ShallowDreamTools/my_lambda.py
ShallowDreamTools-1.2.4.data/data/requirements.txt
db/Functions.py
db/Lambdas.py
db/__init__.py
ShallowDreamTools-1.2.4.dist-info/LICENSE
ShallowDreamTools-1.2.4.dist-info/METADATA
ShallowDreamTools-1.2.4.dist-info/WHEEL
ShallowDreamTools-1.2.4.dist-info/top_level.txt
ShallowDreamTools-1.2.4.dist-info/RECORD
