Metadata-Version: 2.1
Name: ShallowDreamTools
Version: 1.2.4
Summary: ShallowDream's pwn more tools
Home-page: https://pypi.org/project/ShallowDreamTools/
Author: ShallowDream
Author-email: 2547805709@qq.com
Classifier: Programming Language :: Python :: 3
Classifier: License :: OSI Approved :: MIT License
Classifier: Operating System :: OS Independent
Requires-Python: >=3.6
License-File: LICENSE
